Metadata-Version: 2.4
Name: time-server-mcp-ww
Version: 0.1.0
Summary: A time server tool built with FastMCP that provides current time information
Author-email: Your Name <your.email@example.com>
Project-URL: Homepage, https://github.com/yourusername/time-server-mcp
Project-URL: Bug Tracker, https://github.com/yourusername/time-server-mcp/issues
Classifier: Programming Language :: Python :: 3
Classifier: License :: OSI Approved :: MIT License
Classifier: Operating System :: OS Independent
Requires-Python: >=3.8
License-File: LICENSE
Requires-Dist: pytz>=2023.3
Requires-Dist: mcp-server>=0.1.0
Dynamic: license-file
